Workbook
Name Aporte: Investimentos!$D$14
Name Patrimonio: Investimentos!$D$18
Name Perfil: Investimentos!$D$29
Name Qtd_Anos: Investimentos!$D$15
Name Rendimento_Carteira: Investimentos!$D$11
Name Salario: Investimentos!$D$9
Name Sugestao_Investimento: Investimentos!$D$10
Name Taxa_Mensal: Investimentos!$D$16
Name Taxa_Rendimento: Investimentos!$D$16
Name Valor_Investido: Investimentos!$D$17

Sheet Investimentos
B8: CONFIGURACOES
B9: Salario | D9: 15000
B10: Sugestao de Investimento | D10: =Salario*30% -> 4500
B11: Rendimento Carteira | D11: 0.0089
B13: INVESTIMENTOS
B14: Quanto investir por mês? | D14: 3000
B15: Quantos anos de investimento ? | D15: 5
B16: Qual a taxa de rendimento mensal? | D16: 0.01079
B17: Qual o valor total já investido? | D17: =D14*(D15*12) -> 180000
B18: Qual o patrimonio acumulado? | D18: =FV(Taxa_Mensal,(Qtd_Anos*12),(Aporte*-1)) -> 251330.74
B19: Qual o lucro? | D19: =Patrimonio-Valor_Investido -> 71330.742
B20: Quanto serão meus dividendos mensais? | D20: =Patrimonio*Rendimento_Carteira -> 2236.8436
B22: CENARIOS ANUAIS | D22: DIVIDENDOS
A23: 2 | B23: Quanto em 2 anos? | C23: =FV($D$16,(A23*12),($D$14*-1)) -> 81682.882 | D23: =C23*Rendimento_Carteira -> 726.97765
A24: 5 | B24: Quanto em 5 anos? | C24: =FV($D$16,(A24*12),($D$14*-1)) -> 251330.74 | D24: =C24*Rendimento_Carteira -> 2236.8436
A25: 10 | B25: Quanto em 10 anos? | C25: =FV($D$16,(A25*12),($D$14*-1)) -> 729852.64 | D25: =C25*Rendimento_Carteira -> 6495.6885
A26: 20 | B26: Quanto em 20 anos? | C26: =FV($D$16,(A26*12),($D$14*-1)) -> 3375595.2 | D26: =C26*Rendimento_Carteira -> 30042.797
A27: 30 | B27: Quanto em 30 anos? | C27: =FV($D$16,(A27*12),($D$14*-1)) -> 12966509 | D27: =C27*Rendimento_Carteira -> 115401.93
B29: PERFIL | C29: Escolha um perfil | D29: Agressivo
B30: VALOR INVESTIDO POR MES | D30: =Aporte -> 3000
B32: TIPO DE FII | C32: Percentual Sugerido | D32: Valores
B33: PAPEL | C33: =VLOOKUP(Perfil&"-"&B33,Planilha_Apoio!$B$3:$E$20,4,0) -> 0.45 | D33: =C33*Aporte -> 1350
B34: TIJOLO | C34: =VLOOKUP(Perfil&"-"&B34,Planilha_Apoio!$B$3:$E$20,4,0) -> 0.1 | D34: =C34*Aporte -> 300
B35: HIBRIDOS | C35: =VLOOKUP(Perfil&"-"&B35,Planilha_Apoio!$B$3:$E$20,4,0) -> 0.05 | D35: =C35*Aporte -> 150
B36: FOFs | C36: =VLOOKUP(Perfil&"-"&B36,Planilha_Apoio!$B$3:$E$20,4,0) -> 0.05 | D36: =C36*Aporte -> 150
B37: DESENVOLVIMENTO | C37: =VLOOKUP(Perfil&"-"&B37,Planilha_Apoio!$B$3:$E$20,4,0) -> 0.2 | D37: =C37*Aporte -> 600
B38: HOTELARIAS | C38: =VLOOKUP(Perfil&"-"&B38,Planilha_Apoio!$B$3:$E$20,4,0) -> 0.15 | D38: =C38*Aporte -> 450
C39: =SUM(C33:C38) -> 1 | D39: =SUM(D33:D38) -> 3000

Sheet Planilha_Apoio
B2: CHAVE | C2: PERFIL | D2: TIPO DE FII | E2: %
B3: Conservador-PAPEL | C3: Conservador | D3: PAPEL | E3: 0.3
B4: Conservador-TIJOLO | C4: Conservador | D4: TIJOLO | E4: 0.5
B5: Conservador-HIBRIDOS | C5: Conservador | D5: HIBRIDOS | E5: 0.1
B6: Conservador-FOFs | C6: Conservador | D6: FOFs | E6: 0.1
B7: Conservador-DESENVOLVIMENTO | C7: Conservador | D7: DESENVOLVIMENTO | E7: 0
B8: Conservador-HOTELARIAS | C8: Conservador | D8: HOTELARIAS | E8: 0
B9: Moderado-PAPEL | C9: Moderado | D9: PAPEL | E9: 0.32
B10: Moderado-TIJOLO | C10: Moderado | D10: TIJOLO | E10: 0.35
B11: Moderado-HIBRIDOS | C11: Moderado | D11: HIBRIDOS | E11: 0.1
B12: Moderado-FOFs | C12: Moderado | D12: FOFs | E12: 0.05
B13: Moderado-DESENVOLVIMENTO | C13: Moderado | D13: DESENVOLVIMENTO | E13: 0.08
B14: Moderado-HOTELARIAS | C14: Moderado | D14: HOTELARIAS | E14: 0.1
... B20: Agressivo-HOTELARIAS | C20: Agressivo | D20: HOTELARIAS | E20: 0.15
